axiomatic_verifier/__init__.py
axiomatic_verifier/jcs.py
axiomatic_verifier/verifier.py
axiomatic_verifier-0.1.1.dist-info/METADATA
axiomatic_verifier-0.1.1.dist-info/WHEEL
axiomatic_verifier-0.1.1.dist-info/top_level.txt
axiomatic_verifier-0.1.1.dist-info/RECORD
