Metadata-Version: 2.4
Name: axiomatic_verifier
Version: 0.1.1
Requires-Python: >=3.10
Requires-Dist: requests<3.0,>=2.31
